pykeystore/__init__.py
pykeystore/__main__.py
pykeystore/keyringstore.py
pykeystore/keystore.py
pykeystore/keystorex.py
pykeystore/password.py
pykeystore/tests.py
pykeystore-1.1.5.dist-info/LICENSE
pykeystore-1.1.5.dist-info/METADATA
pykeystore-1.1.5.dist-info/WHEEL
pykeystore-1.1.5.dist-info/entry_points.txt
pykeystore-1.1.5.dist-info/top_level.txt
pykeystore-1.1.5.dist-info/RECORD
