Metadata-Version: 2.1
Name: pykeystore
Version: 1.1.5
Summary: Python keystore
Home-page: https://github.com/pe2mbs/pykeystore
Author: Marc Bertens-Nguyen
Author-email: Marc Berten-Nguyen <m.bertens@pe2mbs.nl>
Project-URL: Homepage, https://github.com/pe2mbs/pykeystore
Project-URL: Bug Tracker, https://github.com/pe2mbs/pykeystore/issues
Classifier: Programming Language :: Python :: 3
Classifier: Intended Audience :: Developers
Classifier: License :: OSI Approved :: GNU General Public License v2 (GPLv2)
Classifier: Operating System :: OS Independent
Classifier: Topic :: Security :: Cryptography
Requires-Python: >=3.8
License-File: LICENSE
Requires-Dist: cryptography (>=38.0.1)
Requires-Dist: keyring (>=23.13.1)
Requires-Dist: chardet
